<?xml version="1.0"?>
<houses>
	<house name="Karakura House 1" houseid="1" entryx="3530" entryy="3506" entryz="7" rent="0" townid="1" size="68" />
	<house name="Karakura House 2" houseid="2" entryx="3510" entryy="3516" entryz="7" rent="0" townid="1" size="61" />
	<house name="Karakura House 3" houseid="3" entryx="3514" entryy="3504" entryz="7" rent="0" townid="1" size="42" />
	<house name="Karakura House 4" houseid="4" entryx="3517" entryy="3494" entryz="7" rent="0" townid="1" size="61" />
	<house name="Karakura House 5" houseid="5" entryx="3517" entryy="3489" entryz="7" rent="0" townid="1" size="70" />
	<house name="Karakura House 6" houseid="6" entryx="3512" entryy="3501" entryz="6" rent="0" townid="1" size="49" />
	<house name="Karakura House 7" houseid="7" entryx="3510" entryy="3493" entryz="5" rent="0" townid="1" size="49" />
	<house name="Karakura House 8" houseid="8" entryx="3514" entryy="3489" entryz="6" rent="0" townid="1" size="49" />
	<house name="Karakura House 9" houseid="9" entryx="3526" entryy="3489" entryz="6" rent="0" townid="1" size="63" />
	<house name="Karakura House 10" houseid="10" entryx="3532" entryy="3492" entryz="5" rent="0" townid="1" size="42" />
	<house name="Karakura House 11" houseid="11" entryx="3514" entryy="3512" entryz="6" rent="0" townid="1" size="56" />
	<house name="Karakura House 12" houseid="12" entryx="3511" entryy="3513" entryz="5" rent="0" townid="1" size="35" />
	<house name="Karakura House 13" houseid="13" entryx="3530" entryy="3501" entryz="7" rent="0" townid="1" size="68" />
	<house name="Karakura House 14" houseid="14" entryx="3522" entryy="3489" entryz="7" rent="0" townid="1" size="77" />
	<house name="Karakura House 15" houseid="15" entryx="3542" entryy="3483" entryz="7" rent="0" townid="1" size="54" />
	<house name="Karakura House 16" houseid="16" entryx="3552" entryy="3483" entryz="7" rent="0" townid="1" size="54" />
	<house name="Karakura House 17" houseid="17" entryx="3552" entryy="3499" entryz="7" rent="0" townid="1" size="54" />
	<house name="Karakura House 18" houseid="18" entryx="3542" entryy="3499" entryz="7" rent="0" townid="1" size="54" />
	<house name="Karakura House 19" houseid="19" entryx="3541" entryy="3494" entryz="6" rent="0" townid="1" size="56" />
	<house name="Karakura House 20" houseid="20" entryx="3551" entryy="3491" entryz="6" rent="0" townid="1" size="55" />
	<house name="Karakura House 21" houseid="21" entryx="3550" entryy="3487" entryz="5" rent="0" townid="1" size="25" />
	<house name="Karakura House 22" houseid="22" entryx="3546" entryy="3487" entryz="5" rent="0" townid="1" size="56" />
	<house name="Karakura House 23" houseid="23" entryx="3552" entryy="3477" entryz="7" rent="0" townid="1" size="72" />
	<house name="Karakura House 24" houseid="24" entryx="3543" entryy="3477" entryz="7" rent="0" townid="1" size="48" />
	<house name="Karakura House 25" houseid="25" entryx="3548" entryy="3464" entryz="7" rent="0" townid="1" size="56" />
	<house name="Karakura House 26" houseid="26" entryx="3548" entryy="3456" entryz="7" rent="0" townid="1" size="72" />
	<house name="Karakura House 27" houseid="27" entryx="3545" entryy="3455" entryz="6" rent="0" townid="1" size="25" />
	<house name="Karakura House 28" houseid="28" entryx="3545" entryy="3460" entryz="6" rent="0" townid="1" size="25" />
	<house name="Karakura House 29" houseid="29" entryx="3543" entryy="3458" entryz="5" rent="0" townid="1" size="25" />
	<house name="Karakura House 30" houseid="30" entryx="3547" entryy="3474" entryz="6" rent="0" townid="1" size="44" />
	<house name="Karakura House 31" houseid="31" entryx="3544" entryy="3474" entryz="5" rent="0" townid="1" size="32" />
	<house name="Karakura House 32" houseid="32" entryx="3542" entryy="3474" entryz="4" rent="0" townid="1" size="20" />
	<house name="Karakura House 33" houseid="33" entryx="3549" entryy="3474" entryz="6" rent="0" townid="1" size="79" />
	<house name="Karakura House 34" houseid="34" entryx="3568" entryy="3456" entryz="7" rent="0" townid="1" size="24" />
	<house name="Karakura House 35" houseid="35" entryx="3568" entryy="3463" entryz="7" rent="0" townid="1" size="24" />
	<house name="Karakura House 36" houseid="36" entryx="3571" entryy="3459" entryz="6" rent="0" townid="1" size="20" />
	<house name="Karakura House 37" houseid="37" entryx="3568" entryy="3473" entryz="7" rent="0" townid="1" size="25" />
	<house name="Karakura House 38" houseid="38" entryx="3575" entryy="3473" entryz="7" rent="0" townid="1" size="24" />
	<house name="Karakura House 39" houseid="39" entryx="3581" entryy="3473" entryz="7" rent="0" townid="1" size="25" />
	<house name="Karakura House 40" houseid="40" entryx="3581" entryy="3488" entryz="7" rent="0" townid="1" size="34" />
	<house name="Karakura House 41" houseid="41" entryx="3568" entryy="3488" entryz="7" rent="0" townid="1" size="34" />
	<house name="Karakura House 42" houseid="42" entryx="3577" entryy="3477" entryz="6" rent="0" townid="1" size="98" />
	<house name="Karakura House 43" houseid="43" entryx="3573" entryy="3477" entryz="6" rent="0" townid="1" size="24" />
	<house name="Karakura House 44" houseid="44" entryx="3568" entryy="3482" entryz="6" rent="0" townid="1" size="19" />
	<house name="Karakura House 45" houseid="45" entryx="3569" entryy="3494" entryz="7" rent="0" townid="1" size="42" />
	<house name="Karakura House 46" houseid="46" entryx="3576" entryy="3494" entryz="7" rent="0" townid="1" size="42" />
	<house name="Karakura House 47" houseid="47" entryx="3583" entryy="3494" entryz="7" rent="0" townid="1" size="42" />
	<house name="Karakura House 48" houseid="48" entryx="3592" entryy="3494" entryz="7" rent="0" townid="1" size="70" />
	<house name="Karakura House 49" houseid="49" entryx="3603" entryy="3494" entryz="7" rent="0" townid="1" size="63" />
	<house name="Karakura House 50" houseid="50" entryx="3598" entryy="3508" entryz="7" rent="0" townid="1" size="64" />
	<house name="Karakura House 51" houseid="51" entryx="3604" entryy="3520" entryz="7" rent="0" townid="1" size="48" />
	<house name="Karakura House 52" houseid="52" entryx="3593" entryy="3511" entryz="7" rent="0" townid="1" size="66" />
	<house name="Karakura House 53" houseid="53" entryx="3594" entryy="3502" entryz="6" rent="0" townid="1" size="35" />
	<house name="Karakura House 54" houseid="54" entryx="3597" entryy="3501" entryz="6" rent="0" townid="1" size="24" />
	<house name="Karakura House 55" houseid="55" entryx="3604" entryy="3501" entryz="6" rent="0" townid="1" size="28" />
	<house name="Karakura House 56" houseid="56" entryx="3594" entryy="3498" entryz="5" rent="0" townid="1" size="35" />
	<house name="Karakura House 57" houseid="57" entryx="3599" entryy="3498" entryz="5" rent="0" townid="1" size="28" />
	<house name="Karakura House 58" houseid="58" entryx="3602" entryy="3508" entryz="6" rent="0" townid="1" size="28" />
	<house name="Karakura House 59" houseid="59" entryx="3606" entryy="3510" entryz="5" rent="0" townid="1" size="16" />
	<house name="Karakura House 60" houseid="60" entryx="3600" entryy="3516" entryz="6" rent="0" townid="1" size="66" />
	<house name="Karakura House 61" houseid="61" entryx="3597" entryy="3515" entryz="5" rent="0" townid="1" size="48" />
	<house name="Karakura House 62" houseid="62" entryx="3578" entryy="3500" entryz="6" rent="0" townid="1" size="42" />
	<house name="Karakura House 63" houseid="63" entryx="3573" entryy="3500" entryz="6" rent="0" townid="1" size="42" />
	<house name="Karakura House 64" houseid="64" entryx="3570" entryy="3501" entryz="5" rent="0" townid="1" size="24" />
	<house name="Karakura House 65" houseid="65" entryx="3603" entryy="3467" entryz="7" rent="0" townid="1" size="169" />
</houses>
